jmessaging/__init__.py
jmessaging/jcolor.py
jmessaging/jmessaging.py
jmessaging/jprint.py
jmessaging-0.2.0.dist-info/LICENSE
jmessaging-0.2.0.dist-info/METADATA
jmessaging-0.2.0.dist-info/WHEEL
jmessaging-0.2.0.dist-info/top_level.txt
jmessaging-0.2.0.dist-info/RECORD
