Metadata-Version: 2.1
Name: jmessaging
Version: 0.2.0
Summary: Make printing colorized messages to terminal easier
Home-page: https://github.com/jay3ss/jmessaging
Author: Jay Ess
License: MIT
Platform: UNKNOWN
